odoo/addons/mail_layout_preview/README.rst
odoo/addons/mail_layout_preview/__init__.py
odoo/addons/mail_layout_preview/__manifest__.py
odoo/addons/mail_layout_preview/controllers/__init__.py
odoo/addons/mail_layout_preview/controllers/layout_preview.py
odoo/addons/mail_layout_preview/i18n/mail_layout_preview.pot
odoo/addons/mail_layout_preview/readme/CONTRIBUTORS.rst
odoo/addons/mail_layout_preview/readme/DESCRIPTION.rst
odoo/addons/mail_layout_preview/readme/USAGE.rst
odoo/addons/mail_layout_preview/static/description/icon.png
odoo/addons/mail_layout_preview/static/description/index.html
odoo/addons/mail_layout_preview/templates/email_preview.xml
odoo/addons/mail_layout_preview/tests/__init__.py
odoo/addons/mail_layout_preview/tests/test_layout_preview.py
odoo/addons/mail_layout_preview/wizard/__init__.py
odoo/addons/mail_layout_preview/wizard/email_template_preview.py
odoo/addons/mail_layout_preview/wizard/email_template_preview.xml
odoo13_addon_mail_layout_preview-13.0.1.0.1.dev7.dist-info/METADATA
odoo13_addon_mail_layout_preview-13.0.1.0.1.dev7.dist-info/WHEEL
odoo13_addon_mail_layout_preview-13.0.1.0.1.dev7.dist-info/top_level.txt
odoo13_addon_mail_layout_preview-13.0.1.0.1.dev7.dist-info/RECORD
